zephyr_behave/__init__.py
zephyr_behave/formatter.py
zephyr_behave-1.2.1.dist-info/METADATA
zephyr_behave-1.2.1.dist-info/WHEEL
zephyr_behave-1.2.1.dist-info/top_level.txt
zephyr_behave-1.2.1.dist-info/RECORD
